GamELY/__init__.py
GamELY/core.py
GamELY/provider_mapper.py
gamely-0.1.0.dist-info/licenses/LICENSE
gamely-0.1.0.dist-info/METADATA
gamely-0.1.0.dist-info/WHEEL
gamely-0.1.0.dist-info/top_level.txt
gamely-0.1.0.dist-info/RECORD
