Metadata-Version: 2.4
Name: GamELY
Version: 0.1.0
Summary: A Python package for evaluating LLM-generated responses against human references using state-of-the-art LLMs as judges.
Author-email: Nishant Singh <nishant1695@gmail.com>, Ragahv Awasthi <raghavaw@iiitd.ac.in>
License-Expression: MIT
Project-URL: Homepage, https://github.com/nishant1695/GamELY
Classifier: Programming Language :: Python :: 3
Classifier: Operating System :: OS Independent
Requires-Python: >=3.9
License-File: LICENSE
Dynamic: license-file
